nielvis/__init__.py
nielvis/academicIO.py
nielvis/enums.py
nielvis/bitfile/ELVIS III v2.1 FPGA.lvbitx
nielvis-2.2.8.dist-info/LICENSE
nielvis-2.2.8.dist-info/METADATA
nielvis-2.2.8.dist-info/WHEEL
nielvis-2.2.8.dist-info/top_level.txt
nielvis-2.2.8.dist-info/RECORD
